homechart.py
homechart-2025.12.24.dist-info/licenses/LICENSE
homechart-2025.12.24.dist-info/METADATA
homechart-2025.12.24.dist-info/WHEEL
homechart-2025.12.24.dist-info/top_level.txt
homechart-2025.12.24.dist-info/RECORD
