Metadata-Version: 2.4
Name: homechart
Version: 2025.12.24
Summary: Python library for interacting with the Homechart API
Home-page: https://github.com/candiddev/homechart-python
Author: Candid Development
Author-email: support@candid.dev
Classifier: Programming Language :: Python :: 3
Classifier: License :: OSI Approved :: MIT License
Classifier: Operating System :: OS Independent
Requires-Python: >=3.9
License-File: LICENSE
Dynamic: author
Dynamic: author-email
Dynamic: classifier
Dynamic: description
Dynamic: description-content-type
Dynamic: home-page
Dynamic: license-file
Dynamic: requires-python
Dynamic: summary
